<?xml version="1.0" encoding="UTF-8" standalone="yes"?>
<core:serverDefinition xmlns:core="http://www.enactor.com/core" xmlns:retail="http://www.enactor.com/retail" xmlns:sref="http://docs.oasis-open.org/wsbpel/2.0/serviceref" xmlns:tools="http://www.enactor.com/tools" xmlns:xsi="http://www.w3.org/2001/XMLSchema-instance">
    <core:serverQName>core:receivedSequenceNumber</core:serverQName>
    <core:listMetaData>
        <core:listName>listAll</core:listName>
        <core:pagingSupported>true</core:pagingSupported>
        <core:filters>
            <core:listFilterMetaData>
                <core:id>ID</core:id>
                <core:propertyNames>id</core:propertyNames>
                <core:supportsMultiples>false</core:supportsMultiples>
            </core:listFilterMetaData>
            <core:listFilterMetaData>
                <core:id>Source</core:id>
                <core:propertyNames>source</core:propertyNames>
                <core:supportsMultiples>false</core:supportsMultiples>
            </core:listFilterMetaData>
            <core:listFilterMetaData>
                <core:id>SourceApplication</core:id>
                <core:propertyNames>sourceApplication</core:propertyNames>
                <core:supportsMultiples>false</core:supportsMultiples>
            </core:listFilterMetaData>
            <core:listFilterMetaData>
                <core:id>Topic</core:id>
                <core:propertyNames>topic</core:propertyNames>
                <core:supportsMultiples>false</core:supportsMultiples>
            </core:listFilterMetaData>
            <core:listFilterMetaData>
                <core:id>SequenceNumber</core:id>
                <core:propertyNames>sequenceNumber</core:propertyNames>
                <core:supportsMultiples>false</core:supportsMultiples>
            </core:listFilterMetaData>
            <core:listFilterMetaData>
                <core:id>SequenceNumberMax</core:id>
                <core:propertyNames>sequenceNumber</core:propertyNames>
                <core:supportsMultiples>false</core:supportsMultiples>
            </core:listFilterMetaData>
            <core:listFilterMetaData>
                <core:id>Status</core:id>
                <core:propertyNames>status</core:propertyNames>
                <core:supportsMultiples>false</core:supportsMultiples>
            </core:listFilterMetaData>
            <core:listFilterMetaData>
                <core:id>DateReceived</core:id>
                <core:propertyNames>dateReceived</core:propertyNames>
                <core:supportsMultiples>false</core:supportsMultiples>
            </core:listFilterMetaData>
        </core:filters>
    </core:listMetaData>
    <core:listMetaData>
        <core:listName>listMissings</core:listName>
        <core:pagingSupported>true</core:pagingSupported>
        <core:filters>
            <core:listFilterMetaData>
                <core:id>Source</core:id>
                <core:propertyNames>source</core:propertyNames>
                <core:supportsMultiples>false</core:supportsMultiples>
            </core:listFilterMetaData>
            <core:listFilterMetaData>
                <core:id>SourceApplication</core:id>
                <core:propertyNames>sourceApplication</core:propertyNames>
                <core:supportsMultiples>false</core:supportsMultiples>
            </core:listFilterMetaData>
            <core:listFilterMetaData>
                <core:id>Topic</core:id>
                <core:propertyNames>topic</core:propertyNames>
                <core:supportsMultiples>false</core:supportsMultiples>
            </core:listFilterMetaData>
            <core:listFilterMetaData>
                <core:id>StartDate</core:id>
                <core:propertyNames>dateReceived</core:propertyNames>
                <core:supportsMultiples>false</core:supportsMultiples>
            </core:listFilterMetaData>
            <core:listFilterMetaData>
                <core:id>EndDate</core:id>
                <core:propertyNames>dateReceived</core:propertyNames>
                <core:supportsMultiples>false</core:supportsMultiples>
            </core:listFilterMetaData>
        </core:filters>
    </core:listMetaData>
    <core:listMetaData>
        <core:listName>listSources</core:listName>
        <core:pagingSupported>true</core:pagingSupported>
        <core:filters>
            <core:listFilterMetaData>
                <core:id>Source</core:id>
                <core:propertyNames>source</core:propertyNames>
                <core:supportsMultiples>false</core:supportsMultiples>
            </core:listFilterMetaData>
            <core:listFilterMetaData>
                <core:id>SourceApplication</core:id>
                <core:propertyNames>sourceApplication</core:propertyNames>
                <core:supportsMultiples>false</core:supportsMultiples>
            </core:listFilterMetaData>
            <core:listFilterMetaData>
                <core:id>Topic</core:id>
                <core:propertyNames>topic</core:propertyNames>
                <core:supportsMultiples>false</core:supportsMultiples>
            </core:listFilterMetaData>
        </core:filters>
    </core:listMetaData>
</core:serverDefinition>
