<?xml version="1.0" encoding="UTF-8" standalone="yes"?>
<core:messageResource xmlns:core="http://www.enactor.com/core" xmlns:retail="http://www.enactor.com/retail" xmlns:ns4="http://www.enactor.com/crm" xmlns:hta="http://docs.oasis-open.org/ns/bpel4people/ws-humantask/api/200803" xmlns:ns6="http://www.apis-it.hr/fin/2012/types/f73" xmlns:ns7="http://www.w3.org/2000/09/xmldsig#" xmlns:ns8="http://www.enactor.com/retail/storedRetailTransaction/service" xmlns:ns9="http://www.fu.gov.si/" xmlns:ns10="http://www.enactor.com/addressLookup/service" xmlns:htd="http://docs.oasis-open.org/ns/bpel4people/ws-humantask/200803" xmlns:htt="http://docs.oasis-open.org/ns/bpel4people/ws-humantask/types/200803" xmlns:sref="http://docs.oasis-open.org/wsbpel/2.0/serviceref" xmlns:ns14="http://www.enactor.com/crm/customerLoyalty/service" xmlns:xsi="http://www.w3.org/2001/XMLSchema-instance">
    <core:basename>Pos/Location/LocationMessages</core:basename>
    <core:localeKey></core:localeKey>
    <core:message key="RESOURCE_FRIENDLY_NAME">Location</core:message>
    <core:message key="LOCATION_ID_HEADER">ID</core:message>
    <core:message key="LOCATION_NAME_HEADER">Name</core:message>
    <core:message key="LOCATION_ADDRESS_HEADER">Address</core:message>
    <core:message key="LOCATION_CRITERIA_TITLE">Location Search</core:message>
    <core:message key="LOCATION_CRITERIA_PROMPT">Please enter location name and press search</core:message>
    <core:message key="LOCATION_CRITERIA_NAME">Location Name</core:message>
    <core:message key="LOCATION_CRITERIA_SEARCH_INPUT_TEXT">Please enter a full or partial store name</core:message>
    <core:message key="LOCATION_CRITERIA_BUTTON_SEARCH">Search</core:message>
    <core:message key="LOCATION_CRITERIA_BUTTON_USE_THIS_STORE">Use This Store</core:message>
    <core:message key="LOCATION_CRITERIA_NO_LOCATIONS_FOUND">No stores found.</core:message>
    <core:message key="SELECT_LOCATION_SIMPLE_TITLE">Select Location Simple List</core:message>
    <core:message key="SELECT_LOCTION_STORE_COLLECTION_PROMPT">Please select the store for collection</core:message>
    <core:message key="SELECT_LOCATION_STORE_COLLECTION_EMPTY_LIST">No Stores found for your selection. Please change your search criteria</core:message>
    <core:message key="SELECT_LOCATION_LABEL">Please select a location or filter using the prompt below.</core:message>
    <core:message key="NO_LOCATION_SELECTED">No location selected</core:message>
</core:messageResource>
