<?xml version="1.0" encoding="UTF-8" standalone="yes"?>
<core:process xmlns:core="http://www.enactor.com/core" xmlns:retail="http://www.enactor.com/retail" xmlns:ns4="http://www.enactor.com/crm" xmlns:hta="http://docs.oasis-open.org/ns/bpel4people/ws-humantask/api/200803" xmlns:ns6="http://www.apis-it.hr/fin/2012/types/f73" xmlns:ns7="http://www.w3.org/2000/09/xmldsig#" xmlns:ns8="http://www.enactor.com/retail/storedRetailTransaction/service" xmlns:ns9="http://www.fu.gov.si/" xmlns:ns10="http://www.enactor.com/addressLookup/service" xmlns:htd="http://docs.oasis-open.org/ns/bpel4people/ws-humantask/200803" xmlns:htt="http://docs.oasis-open.org/ns/bpel4people/ws-humantask/types/200803" xmlns:sref="http://docs.oasis-open.org/wsbpel/2.0/serviceref" xmlns:ns14="http://www.enactor.com/crm/customerLoyalty/service" xmlns:xsi="http://www.w3.org/2001/XMLSchema-instance">
    <core:processID>CRM/Customer/ViewProductSuggestions</core:processID>
    <core:version>1.0</core:version>
    <core:name></core:name>
    <core:defaultMessageBaseName></core:defaultMessageBaseName>
    <core:firstStateID>Start</core:firstStateID>
    <core:className></core:className>
    <core:uiHints>
        <entry>
            <key>com.enactor.tools.editor.process.style</key>
            <value>1023</value>
        </entry>
        <entry>
            <key>com.enactor.tools.editor.process.xloc</key>
            <value>8</value>
        </entry>
        <entry>
            <key>com.enactor.tools.editor.process.yloc</key>
            <value>8</value>
        </entry>
    </core:uiHints>
    <core:metaData>
        <core:inputs>
            <core:input required="true" name="enactor.mfc.Customer">
                <core:interfaceName>com.enactor.mfc.customer.ICustomer</core:interfaceName>
            </core:input>
            <core:input required="true" name="enactor.mfc.BaseCurrency">
                <core:interfaceName>com.enactor.mfc.currency.ICurrency</core:interfaceName>
            </core:input>
            <core:input required="true" name="enactor.customerMaintenance.CustomerLoyaltyDetailResponse">
                <core:interfaceName>com.enactor.crm.customerLoyalty.ICustomerLoyaltyDetailResponse</core:interfaceName>
            </core:input>
            <core:input required="true" name="enactor.coreUI.URL">
                <core:interfaceName>java.lang.String</core:interfaceName>
            </core:input>
            <core:input required="true" name="enactor.mfc.Location">
                <core:interfaceName>com.enactor.mfc.location.ILocation</core:interfaceName>
            </core:input>
            <core:input required="true" name="enactor.mfc.Device">
                <core:interfaceName>com.enactor.mfc.device.IDevice</core:interfaceName>
            </core:input>
        </core:inputs>
        <stateDataTypes>
            <stateDataType required="true" name="enactor.coreUI.ListCriteria">
                <core:interfaceName>com.enactor.core.servers.IListCriteria</core:interfaceName>
            </stateDataType>
            <stateDataType required="true" name="enactor.mfc.CustomerPreferenceList">
                <core:interfaceName>java.util.List</core:interfaceName>
            </stateDataType>
            <stateDataType required="true" name="enactor.mfc.Customer">
                <core:interfaceName>com.enactor.mfc.customer.ICustomer</core:interfaceName>
            </stateDataType>
            <stateDataType required="true" name="enactor.customerMaintenance.CustomerLoyaltyDetailResponse">
                <core:interfaceName>com.enactor.crm.customerLoyalty.ICustomerLoyaltyDetailResponse</core:interfaceName>
            </stateDataType>
            <stateDataType required="true" name="enactor.mfc.BaseCurrency">
                <core:interfaceName>com.enactor.mfc.currency.ICurrency</core:interfaceName>
            </stateDataType>
            <stateDataType required="true" name="enactor.mfc.Location">
                <core:interfaceName>com.enactor.mfc.location.ILocation</core:interfaceName>
            </stateDataType>
            <stateDataType required="true" name="enactor.coreUI.URL">
                <core:interfaceName>java.lang.String</core:interfaceName>
            </stateDataType>
            <stateDataType required="true" name="enactor.mfc.Device">
                <core:interfaceName>com.enactor.mfc.device.IDevice</core:interfaceName>
            </stateDataType>
            <stateDataType required="true" name="enactor.coreUI.List">
                <core:interfaceName>java.util.List</core:interfaceName>
            </stateDataType>
        </stateDataTypes>
    </core:metaData>
    <core:executeProcessAction>
        <core:defaultNextStateID></core:defaultNextStateID>
        <core:actionID>InvokeProductEnquiry</core:actionID>
        <core:name></core:name>
        <core:className>com.enactor.coreUI.actions.UICallProcessAction</core:className>
        <core:uiHints>
            <entry>
                <key>com.enactor.tools.editor.process.style</key>
                <value>1023</value>
            </entry>
            <entry>
                <key>com.enactor.tools.editor.process.xloc</key>
                <value>1664</value>
            </entry>
            <entry>
                <key>com.enactor.tools.editor.process.yloc</key>
                <value>471</value>
            </entry>
        </core:uiHints>
        <core:metaData>
            <core:inputs>
                <core:input required="true" name="enactor.productSearch.ProductId">
                    <core:interfaceName>java.lang.String</core:interfaceName>
                </core:input>
                <core:input name="enactor.productSearch.UserId">
                    <core:interfaceName>java.lang.String</core:interfaceName>
                </core:input>
                <core:input required="true" name="enactor.mfc.Location">
                    <core:interfaceName>com.enactor.mfc.location.ILocation</core:interfaceName>
                </core:input>
                <core:input required="true" name="enactor.mfc.Device">
                    <core:interfaceName>com.enactor.mfc.device.IDevice</core:interfaceName>
                </core:input>
            </core:inputs>
            <core:outputs>
                <core:output required="true" name="enactor.productSearch.ProductEnquiryResponse">
                    <core:interfaceName>com.enactor.mfc.product.enquiry.IProductEnquiryResponse</core:interfaceName>
                </core:output>
            </core:outputs>
            <core:outcomes>
                <core:outcome name="Success"/>
                <core:outcome name="Fail"/>
            </core:outcomes>
        </core:metaData>
        <core:typeId>enactor.types.CallProcess</core:typeId>
        <core:outcomeLink>
            <core:linkID>1</core:linkID>
            <core:toStateID>ProductDetails</core:toStateID>
            <core:toActionID></core:toActionID>
            <core:condition></core:condition>
            <core:outcome>Success</core:outcome>
        </core:outcomeLink>
        <core:outcomeLink>
            <core:linkID>2</core:linkID>
            <core:toStateID>ProductDetails</core:toStateID>
            <core:toActionID></core:toActionID>
            <core:condition></core:condition>
            <core:outcome>Fail</core:outcome>
        </core:outcomeLink>
        <core:executeProcessId>CRM/ProductSearch/InvokeProductEnquiry</core:executeProcessId>
    </core:executeProcessAction>
    <core:action>
        <core:defaultNextStateID></core:defaultNextStateID>
        <core:actionID>CustomerNumberFilter</core:actionID>
        <core:name>AddListFilterAction</core:name>
        <core:className>com.enactor.commonUI.list.processes.AddListFilterAction</core:className>
        <core:uiHints>
            <entry>
                <key>com.enactor.tools.editor.process.style</key>
                <value>1023</value>
            </entry>
            <entry>
                <key>com.enactor.tools.editor.process.xloc</key>
                <value>229</value>
            </entry>
            <entry>
                <key>com.enactor.tools.editor.process.yloc</key>
                <value>191</value>
            </entry>
        </core:uiHints>
        <core:param value="CustomerNumber" name="enactor.coreUI.FilterId">
            <core:interfaceName>java.lang.String</core:interfaceName>
        </core:param>
        <core:param value="TextValueFilter" name="enactor.coreUI.FilterType">
            <core:interfaceName>java.lang.String</core:interfaceName>
        </core:param>
        <core:metaData>
            <core:inputs>
                <core:input name="enactor.coreUI.FilterClassname">
                    <core:interfaceName>java.lang.String</core:interfaceName>
                </core:input>
                <core:input name="enactor.coreUI.ListCriteria">
                    <core:interfaceName>com.enactor.core.servers.IListCriteria</core:interfaceName>
                </core:input>
                <core:input name="enactor.coreUI.DefaultToFirstValue">
                    <core:interfaceName>java.lang.Boolean</core:interfaceName>
                </core:input>
                <core:input name="enactor.commonUI.OrNull">
                    <core:interfaceName>java.lang.Boolean</core:interfaceName>
                </core:input>
                <core:input name="enactor.coreUI.FilterKeyProperty">
                    <core:interfaceName>java.lang.String</core:interfaceName>
                </core:input>
                <core:input name="enactor.commonUI.PersistenceGroupId">
                    <core:interfaceName>java.lang.String</core:interfaceName>
                </core:input>
                <core:input name="enactor.coreUI.ListFiltersMap">
                    <core:interfaceName>java.util.Map</core:interfaceName>
                </core:input>
                <core:input name="enactor.coreUI.ListAllowBlank">
                    <core:interfaceName>java.lang.Boolean</core:interfaceName>
                </core:input>
                <core:input name="enactor.coreUI.ListName">
                    <core:interfaceName>java.lang.String</core:interfaceName>
                </core:input>
                <core:input name="enactor.coreUI.EntityName">
                    <core:interfaceName>java.lang.String</core:interfaceName>
                </core:input>
                <core:input name="enactor.coreUI.UseKeyForValue">
                    <core:interfaceName>java.lang.Boolean</core:interfaceName>
                </core:input>
                <core:input name="enactor.coreUI.BlankValue">
                    <core:interfaceName>java.lang.Object</core:interfaceName>
                </core:input>
                <core:input name="enactor.commonUI.ReadOnly">
                    <core:interfaceName>java.lang.Boolean</core:interfaceName>
                </core:input>
                <core:input name="enactor.coreUI.ListFilterHidden">
                    <core:interfaceName>java.lang.Boolean</core:interfaceName>
                </core:input>
                <core:input name="enactor.commonUI.ForceApplicable">
                    <core:interfaceName>java.lang.Boolean</core:interfaceName>
                </core:input>
                <core:input name="enactor.coreUI.FuzzyLevel">
                    <core:interfaceName>java.lang.Integer</core:interfaceName>
                </core:input>
                <core:input name="enactor.coreUI.UseValueForAllProperties">
                    <core:interfaceName>java.lang.Boolean</core:interfaceName>
                </core:input>
                <core:input name="enactor.coreUI.CaseInsensitive">
                    <core:interfaceName>java.lang.Boolean</core:interfaceName>
                </core:input>
                <core:input name="enactor.commonUI.IgnorePersistenceGroupValues">
                    <core:interfaceName>java.lang.Boolean</core:interfaceName>
                </core:input>
                <core:input name="enactor.coreUI.ListFilterWidth">
                    <core:interfaceName>java.lang.Integer</core:interfaceName>
                </core:input>
                <core:input name="enactor.coreUI.EntityNamespace">
                    <core:interfaceName>java.lang.String</core:interfaceName>
                </core:input>
                <core:input name="enactor.coreUI.ValueArray">
                    <core:interfaceName>java.lang.Object</core:interfaceName>
                </core:input>
                <core:input name="enactor.commonUI.ReplaceExistingFilter">
                    <core:interfaceName>java.lang.Boolean</core:interfaceName>
                </core:input>
                <core:input name="enactor.coreUI.FilterType">
                    <core:interfaceName>java.lang.String</core:interfaceName>
                </core:input>
                <core:input name="enactor.coreUI.ListOrProperties">
                    <core:interfaceName>java.lang.Boolean</core:interfaceName>
                </core:input>
                <core:input name="enactor.coreUI.FilterVariableNames">
                    <core:interfaceName>java.lang.String</core:interfaceName>
                </core:input>
                <core:input required="true" name="enactor.coreUI.FilterId">
                    <core:interfaceName>java.lang.String</core:interfaceName>
                </core:input>
                <core:input name="enactor.coreUI.MessageId">
                    <core:interfaceName>java.lang.String</core:interfaceName>
                </core:input>
                <core:input name="enactor.coreUI.MessageBasename">
                    <core:interfaceName>java.lang.String</core:interfaceName>
                </core:input>
                <core:input name="enactor.coreUI.DefaultValue">
                    <core:interfaceName>java.lang.Object</core:interfaceName>
                </core:input>
                <core:input name="enactor.coreUI.CompoundListFilters">
                    <core:interfaceName>java.util.List</core:interfaceName>
                </core:input>
                <core:input name="enactor.coreUI.ComparisonOperator">
                    <core:interfaceName>java.lang.Object</core:interfaceName>
                </core:input>
                <core:input name="enactor.coreUI.ListFilters">
                    <core:interfaceName>java.util.List</core:interfaceName>
                </core:input>
            </core:inputs>
            <core:outputs>
                <core:output name="enactor.coreUI.ListCriteria">
                    <core:interfaceName>com.enactor.core.servers.IListCriteria</core:interfaceName>
                </core:output>
                <core:output name="enactor.coreUI.ListFiltersMap">
                    <core:interfaceName>java.util.Map</core:interfaceName>
                </core:output>
                <core:output name="enactor.coreUI.ListFilter">
                    <core:interfaceName>com.enactor.core.listFilters.IListFilter</core:interfaceName>
                </core:output>
                <core:output name="enactor.coreUI.ListFilters">
                    <core:interfaceName>java.util.List</core:interfaceName>
                </core:output>
            </core:outputs>
            <core:outcomes>
                <core:outcome name="Success"/>
            </core:outcomes>
        </core:metaData>
        <core:outcomeLink>
            <core:linkID>1</core:linkID>
            <core:toStateID></core:toStateID>
            <core:toActionID>OptionSetFilter:Suggestions</core:toActionID>
            <core:condition></core:condition>
            <core:outcome>Success</core:outcome>
        </core:outcomeLink>
    </core:action>
    <core:action>
        <core:defaultNextStateID></core:defaultNextStateID>
        <core:actionID>OptionSetFilter:Suggestions</core:actionID>
        <core:name>AddListFilterAction</core:name>
        <core:className>com.enactor.commonUI.list.processes.AddListFilterAction</core:className>
        <core:uiHints>
            <entry>
                <key>com.enactor.tools.editor.process.style</key>
                <value>1023</value>
            </entry>
            <entry>
                <key>com.enactor.tools.editor.process.xloc</key>
                <value>468</value>
            </entry>
            <entry>
                <key>com.enactor.tools.editor.process.yloc</key>
                <value>191</value>
            </entry>
        </core:uiHints>
        <core:param value="OptionSetId" name="enactor.coreUI.FilterId">
            <core:interfaceName>java.lang.String</core:interfaceName>
        </core:param>
        <core:param value="MatchTextValueFilter" name="enactor.coreUI.FilterType">
            <core:interfaceName>java.lang.String</core:interfaceName>
        </core:param>
        <core:param value="CUSTOMER_PRODUCT_SUGGESTIONS" name="enactor.coreUI.DefaultValue">
            <core:interfaceName>java.lang.Object</core:interfaceName>
        </core:param>
        <core:metaData>
            <core:inputs>
                <core:input name="enactor.coreUI.DefaultToFirstValue">
                    <core:interfaceName>java.lang.Boolean</core:interfaceName>
                </core:input>
                <core:input name="enactor.coreUI.ListCriteria">
                    <core:interfaceName>com.enactor.core.servers.IListCriteria</core:interfaceName>
                </core:input>
                <core:input name="enactor.coreUI.FilterClassname">
                    <core:interfaceName>java.lang.String</core:interfaceName>
                </core:input>
                <core:input name="enactor.commonUI.OrNull">
                    <core:interfaceName>java.lang.Boolean</core:interfaceName>
                </core:input>
                <core:input name="enactor.coreUI.FilterKeyProperty">
                    <core:interfaceName>java.lang.String</core:interfaceName>
                </core:input>
                <core:input name="enactor.commonUI.PersistenceGroupId">
                    <core:interfaceName>java.lang.String</core:interfaceName>
                </core:input>
                <core:input name="enactor.coreUI.ListFiltersMap">
                    <core:interfaceName>java.util.Map</core:interfaceName>
                </core:input>
                <core:input name="enactor.coreUI.ListAllowBlank">
                    <core:interfaceName>java.lang.Boolean</core:interfaceName>
                </core:input>
                <core:input name="enactor.coreUI.UseKeyForValue">
                    <core:interfaceName>java.lang.Boolean</core:interfaceName>
                </core:input>
                <core:input name="enactor.coreUI.EntityName">
                    <core:interfaceName>java.lang.String</core:interfaceName>
                </core:input>
                <core:input name="enactor.coreUI.ListName">
                    <core:interfaceName>java.lang.String</core:interfaceName>
                </core:input>
                <core:input name="enactor.coreUI.BlankValue">
                    <core:interfaceName>java.lang.Object</core:interfaceName>
                </core:input>
                <core:input name="enactor.commonUI.ReadOnly">
                    <core:interfaceName>java.lang.Boolean</core:interfaceName>
                </core:input>
                <core:input name="enactor.coreUI.ListFilterHidden">
                    <core:interfaceName>java.lang.Boolean</core:interfaceName>
                </core:input>
                <core:input name="enactor.commonUI.ForceApplicable">
                    <core:interfaceName>java.lang.Boolean</core:interfaceName>
                </core:input>
                <core:input name="enactor.coreUI.FuzzyLevel">
                    <core:interfaceName>java.lang.Integer</core:interfaceName>
                </core:input>
                <core:input name="enactor.coreUI.UseValueForAllProperties">
                    <core:interfaceName>java.lang.Boolean</core:interfaceName>
                </core:input>
                <core:input name="enactor.coreUI.CaseInsensitive">
                    <core:interfaceName>java.lang.Boolean</core:interfaceName>
                </core:input>
                <core:input name="enactor.commonUI.IgnorePersistenceGroupValues">
                    <core:interfaceName>java.lang.Boolean</core:interfaceName>
                </core:input>
                <core:input name="enactor.coreUI.ListFilterWidth">
                    <core:interfaceName>java.lang.Integer</core:interfaceName>
                </core:input>
                <core:input name="enactor.coreUI.EntityNamespace">
                    <core:interfaceName>java.lang.String</core:interfaceName>
                </core:input>
                <core:input name="enactor.coreUI.ValueArray">
                    <core:interfaceName>java.lang.Object</core:interfaceName>
                </core:input>
                <core:input name="enactor.commonUI.ReplaceExistingFilter">
                    <core:interfaceName>java.lang.Boolean</core:interfaceName>
                </core:input>
                <core:input name="enactor.coreUI.FilterType">
                    <core:interfaceName>java.lang.String</core:interfaceName>
                </core:input>
                <core:input name="enactor.coreUI.ListOrProperties">
                    <core:interfaceName>java.lang.Boolean</core:interfaceName>
                </core:input>
                <core:input name="enactor.coreUI.FilterVariableNames">
                    <core:interfaceName>java.lang.String</core:interfaceName>
                </core:input>
                <core:input required="true" name="enactor.coreUI.FilterId">
                    <core:interfaceName>java.lang.String</core:interfaceName>
                </core:input>
                <core:input name="enactor.coreUI.MessageId">
                    <core:interfaceName>java.lang.String</core:interfaceName>
                </core:input>
                <core:input name="enactor.coreUI.MessageBasename">
                    <core:interfaceName>java.lang.String</core:interfaceName>
                </core:input>
                <core:input name="enactor.coreUI.DefaultValue">
                    <core:interfaceName>java.lang.Object</core:interfaceName>
                </core:input>
                <core:input name="enactor.coreUI.ComparisonOperator">
                    <core:interfaceName>java.lang.Object</core:interfaceName>
                </core:input>
                <core:input name="enactor.coreUI.CompoundListFilters">
                    <core:interfaceName>java.util.List</core:interfaceName>
                </core:input>
                <core:input name="enactor.coreUI.ListFilters">
                    <core:interfaceName>java.util.List</core:interfaceName>
                </core:input>
            </core:inputs>
            <core:outputs>
                <core:output name="enactor.coreUI.ListCriteria">
                    <core:interfaceName>com.enactor.core.servers.IListCriteria</core:interfaceName>
                </core:output>
                <core:output name="enactor.coreUI.ListFiltersMap">
                    <core:interfaceName>java.util.Map</core:interfaceName>
                </core:output>
                <core:output name="enactor.coreUI.ListFilter">
                    <core:interfaceName>com.enactor.core.listFilters.IListFilter</core:interfaceName>
                </core:output>
                <core:output name="enactor.coreUI.ListFilters">
                    <core:interfaceName>java.util.List</core:interfaceName>
                </core:output>
            </core:outputs>
            <core:outcomes>
                <core:outcome name="Success"/>
            </core:outcomes>
        </core:metaData>
        <core:outcomeLink>
            <core:linkID>1</core:linkID>
            <core:toStateID></core:toStateID>
            <core:toActionID>InvokeLoadCustomerPreference</core:toActionID>
            <core:condition></core:condition>
            <core:outcome>Success</core:outcome>
        </core:outcomeLink>
        <core:outcomeLink>
            <core:linkID>2</core:linkID>
            <core:toStateID></core:toStateID>
            <core:toActionID>CallLoadCustomerPreferences</core:toActionID>
            <core:condition>true</core:condition>
            <core:outcome>Success</core:outcome>
        </core:outcomeLink>
    </core:action>
    <core:executeProcessAction>
        <core:defaultNextStateID></core:defaultNextStateID>
        <core:actionID>InvokeLoadCustomerPreference</core:actionID>
        <core:name></core:name>
        <core:className>com.enactor.coreUI.actions.UICallProcessAction</core:className>
        <core:uiHints>
            <entry>
                <key>com.enactor.tools.editor.process.style</key>
                <value>1023</value>
            </entry>
            <entry>
                <key>com.enactor.tools.editor.process.xloc</key>
                <value>707</value>
            </entry>
            <entry>
                <key>com.enactor.tools.editor.process.yloc</key>
                <value>191</value>
            </entry>
        </core:uiHints>
        <core:metaData>
            <core:inputs>
                <core:input required="true" name="enactor.coreUI.ListCriteria">
                    <core:interfaceName>com.enactor.core.servers.IListCriteria</core:interfaceName>
                </core:input>
                <core:input required="true" name="enactor.mfc.Device">
                    <core:interfaceName>com.enactor.mfc.device.IDevice</core:interfaceName>
                </core:input>
            </core:inputs>
            <core:outputs>
                <core:output required="true" name="enactor.coreUI.ListCriteria">
                    <core:interfaceName>com.enactor.core.servers.IListCriteria</core:interfaceName>
                </core:output>
                <core:output required="true" name="enactor.coreUI.List">
                    <core:interfaceName>java.util.List</core:interfaceName>
                </core:output>
            </core:outputs>
            <core:outcomes>
                <core:outcome name="Success"/>
                <core:outcome name="Fail"/>
            </core:outcomes>
        </core:metaData>
        <core:typeId>enactor.types.CallProcess</core:typeId>
        <core:outcomeLink>
            <core:linkID>2</core:linkID>
            <core:toStateID>ProductOverview</core:toStateID>
            <core:toActionID></core:toActionID>
            <core:condition></core:condition>
            <core:outcome>Fail</core:outcome>
        </core:outcomeLink>
        <core:outcomeLink>
            <core:linkID>1</core:linkID>
            <core:toStateID></core:toStateID>
            <core:toActionID>GetProductsListFormPreferencesAction</core:toActionID>
            <core:condition></core:condition>
            <core:outcome>Success</core:outcome>
        </core:outcomeLink>
        <core:executeProcessId>CRM/CustomerMaintenance/InvokeLoadCustomerPreference</core:executeProcessId>
    </core:executeProcessAction>
    <core:executeProcessAction>
        <core:defaultNextStateID></core:defaultNextStateID>
        <core:actionID>CallLoadCustomerPreferences</core:actionID>
        <core:name></core:name>
        <core:className>com.enactor.coreUI.actions.UICallProcessAction</core:className>
        <core:uiHints>
            <entry>
                <key>com.enactor.tools.editor.process.style</key>
                <value>1023</value>
            </entry>
            <entry>
                <key>com.enactor.tools.editor.process.xloc</key>
                <value>707</value>
            </entry>
            <entry>
                <key>com.enactor.tools.editor.process.yloc</key>
                <value>667</value>
            </entry>
        </core:uiHints>
        <core:metaData>
            <core:inputs>
                <core:input required="true" name="enactor.coreUI.ListCriteria">
                    <core:interfaceName>com.enactor.core.servers.IListCriteria</core:interfaceName>
                </core:input>
            </core:inputs>
            <core:outputs>
                <core:output required="false" name="enactor.coreUI.List">
                    <core:interfaceName>java.util.List</core:interfaceName>
                </core:output>
            </core:outputs>
            <core:outcomes>
                <core:outcome name="Exception"/>
                <core:outcome name="Success"/>
            </core:outcomes>
        </core:metaData>
        <core:typeId>enactor.types.CallProcess</core:typeId>
        <core:outcomeLink>
            <core:linkID>2</core:linkID>
            <core:toStateID>ProductOverview</core:toStateID>
            <core:toActionID></core:toActionID>
            <core:condition></core:condition>
            <core:outcome>Exception</core:outcome>
        </core:outcomeLink>
        <core:outcomeLink>
            <core:linkID>1</core:linkID>
            <core:toStateID></core:toStateID>
            <core:toActionID>GetProductsListFormPreferencesAction</core:toActionID>
            <core:condition></core:condition>
            <core:outcome>Success</core:outcome>
        </core:outcomeLink>
        <core:executeProcessId>CRM/CustomerMaintenance/LoadCustomerPreferences</core:executeProcessId>
    </core:executeProcessAction>
    <core:endProcessAction>
        <core:defaultNextStateID></core:defaultNextStateID>
        <core:actionID>Cancel</core:actionID>
        <core:name></core:name>
        <core:className>com.enactor.coreUI.actions.UIEndProcessAction</core:className>
        <core:uiHints>
            <entry>
                <key>com.enactor.tools.editor.process.style</key>
                <value>1</value>
            </entry>
            <entry>
                <key>com.enactor.tools.editor.process.xloc</key>
                <value>707</value>
            </entry>
            <entry>
                <key>com.enactor.tools.editor.process.yloc</key>
                <value>82</value>
            </entry>
        </core:uiHints>
        <core:metaData/>
        <core:typeId>enactor.types.EndProcess</core:typeId>
        <core:outcome>Cancel</core:outcome>
        <core:defaultProcessId></core:defaultProcessId>
    </core:endProcessAction>
    <core:endProcessAction>
        <core:defaultNextStateID></core:defaultNextStateID>
        <core:actionID>View Wish List</core:actionID>
        <core:name></core:name>
        <core:className>com.enactor.coreUI.actions.UIEndProcessAction</core:className>
        <core:uiHints>
            <entry>
                <key>com.enactor.tools.editor.process.style</key>
                <value>1</value>
            </entry>
            <entry>
                <key>com.enactor.tools.editor.process.xloc</key>
                <value>1214</value>
            </entry>
            <entry>
                <key>com.enactor.tools.editor.process.yloc</key>
                <value>82</value>
            </entry>
        </core:uiHints>
        <core:metaData/>
        <core:typeId>enactor.types.EndProcess</core:typeId>
        <core:outcome>ViewWishList</core:outcome>
        <core:defaultProcessId></core:defaultProcessId>
    </core:endProcessAction>
    <core:action>
        <core:defaultNextStateID></core:defaultNextStateID>
        <core:actionID>RemoveProductFromCustomerPreference</core:actionID>
        <core:name></core:name>
        <core:className>com.enactor.crm.customerView.actions.RemoveProductFromCustomerPreferenceAction</core:className>
        <core:uiHints>
            <entry>
                <key>com.enactor.tools.editor.process.style</key>
                <value>1023</value>
            </entry>
            <entry>
                <key>com.enactor.tools.editor.process.xloc</key>
                <value>1664</value>
            </entry>
            <entry>
                <key>com.enactor.tools.editor.process.yloc</key>
                <value>191</value>
            </entry>
        </core:uiHints>
        <core:metaData>
            <core:inputs>
                <core:input required="true" name="enactor.mfc.ProductId">
                    <core:interfaceName>java.lang.String</core:interfaceName>
                </core:input>
                <core:input required="true" name="enactor.coreUI.List">
                    <core:interfaceName>java.util.List</core:interfaceName>
                </core:input>
            </core:inputs>
            <core:outcomes>
                <core:outcome name="Success"/>
            </core:outcomes>
            <core:sessionManagementType>MAKE_SESSION_IF_NO_CURRENT</core:sessionManagementType>
        </core:metaData>
        <core:typeId>enactor.types.BasicAction</core:typeId>
        <core:outcomeLink>
            <core:linkID>1</core:linkID>
            <core:toStateID></core:toStateID>
            <core:toActionID>ReLoadProductsListFormPreferencesAction</core:toActionID>
            <core:condition></core:condition>
            <core:outcome>Success</core:outcome>
        </core:outcomeLink>
    </core:action>
    <core:executeProcessAction>
        <core:defaultNextStateID></core:defaultNextStateID>
        <core:actionID>AddProductToCustomerWishList</core:actionID>
        <core:name></core:name>
        <core:className>com.enactor.coreUI.actions.UICallProcessAction</core:className>
        <core:uiHints>
            <entry>
                <key>com.enactor.tools.editor.process.style</key>
                <value>1023</value>
            </entry>
            <entry>
                <key>com.enactor.tools.editor.process.xloc</key>
                <value>1214</value>
            </entry>
            <entry>
                <key>com.enactor.tools.editor.process.yloc</key>
                <value>693</value>
            </entry>
        </core:uiHints>
        <core:metaData>
            <core:inputs>
                <core:input required="true" name="enactor.mfc.CustomerKey">
                    <core:interfaceName>com.enactor.mfc.customer.ICustomerKey</core:interfaceName>
                </core:input>
                <core:input required="true" name="enactor.mfc.Device">
                    <core:interfaceName>com.enactor.mfc.device.IDevice</core:interfaceName>
                </core:input>
                <core:input required="true" name="enactor.mfc.ProductDescription">
                    <core:interfaceName>java.lang.String</core:interfaceName>
                </core:input>
                <core:input required="true" name="enactor.mfc.ProductId">
                    <core:interfaceName>java.lang.String</core:interfaceName>
                </core:input>
            </core:inputs>
            <core:outcomes>
                <core:outcome name="Success"/>
                <core:outcome name="Fail"/>
            </core:outcomes>
        </core:metaData>
        <core:typeId>enactor.types.CallProcess</core:typeId>
        <core:outcomeLink>
            <core:linkID>1</core:linkID>
            <core:toStateID>ProductDetails</core:toStateID>
            <core:toActionID></core:toActionID>
            <core:condition></core:condition>
            <core:outcome>Fail</core:outcome>
        </core:outcomeLink>
        <core:outcomeLink>
            <core:linkID>2</core:linkID>
            <core:toStateID></core:toStateID>
            <core:toActionID>RemoveProductFromCustomerPreference</core:toActionID>
            <core:condition></core:condition>
            <core:outcome>Success</core:outcome>
        </core:outcomeLink>
        <core:executeProcessId>CRM/Customer/AddProductToCustomerWishList</core:executeProcessId>
    </core:executeProcessAction>
    <core:executeProcessAction>
        <core:defaultNextStateID></core:defaultNextStateID>
        <core:actionID>ReLoadCustomerPreferences</core:actionID>
        <core:name></core:name>
        <core:className>com.enactor.coreUI.actions.UICallProcessAction</core:className>
        <core:uiHints>
            <entry>
                <key>com.enactor.tools.editor.process.style</key>
                <value>1023</value>
            </entry>
            <entry>
                <key>com.enactor.tools.editor.process.xloc</key>
                <value>1214</value>
            </entry>
            <entry>
                <key>com.enactor.tools.editor.process.yloc</key>
                <value>191</value>
            </entry>
        </core:uiHints>
        <core:metaData>
            <core:inputs>
                <core:input required="true" name="enactor.coreUI.ListCriteria">
                    <core:interfaceName>com.enactor.core.servers.IListCriteria</core:interfaceName>
                </core:input>
            </core:inputs>
            <core:outputs>
                <core:output required="false" name="enactor.coreUI.List">
                    <core:interfaceName>java.util.List</core:interfaceName>
                </core:output>
            </core:outputs>
            <core:outcomes>
                <core:outcome name="Exception"/>
                <core:outcome name="Success"/>
            </core:outcomes>
            <core:sessionManagementType>NONE</core:sessionManagementType>
        </core:metaData>
        <core:typeId>enactor.types.CallProcess</core:typeId>
        <core:outcomeLink>
            <core:linkID>2</core:linkID>
            <core:toStateID></core:toStateID>
            <core:toActionID>ReLoadProductsListFormPreferencesAction</core:toActionID>
            <core:condition></core:condition>
            <core:outcome>Success</core:outcome>
        </core:outcomeLink>
        <core:outcomeLink>
            <core:linkID>1</core:linkID>
            <core:toStateID>ProductOverview</core:toStateID>
            <core:toActionID></core:toActionID>
            <core:condition></core:condition>
            <core:outcome>Exception</core:outcome>
        </core:outcomeLink>
        <core:executeProcessId>CRM/CustomerMaintenance/LoadCustomerPreferences</core:executeProcessId>
    </core:executeProcessAction>
    <core:action>
        <core:defaultNextStateID></core:defaultNextStateID>
        <core:actionID>ReLoadProductsListFormPreferencesAction</core:actionID>
        <core:name>GetProductsListFormPreferencesAction</core:name>
        <core:className>com.enactor.crm.customerView.actions.GetProductsListFormPreferencesAction</core:className>
        <core:uiHints>
            <entry>
                <key>com.enactor.tools.editor.process.style</key>
                <value>1023</value>
            </entry>
            <entry>
                <key>com.enactor.tools.editor.process.xloc</key>
                <value>1424</value>
            </entry>
            <entry>
                <key>com.enactor.tools.editor.process.yloc</key>
                <value>191</value>
            </entry>
        </core:uiHints>
        <core:metaData>
            <core:inputs>
                <core:input required="true" name="enactor.coreUI.List">
                    <core:interfaceName>java.util.List</core:interfaceName>
                </core:input>
            </core:inputs>
            <core:outputs>
                <core:output name="enactor.coreUI.List">
                    <core:interfaceName>java.util.List</core:interfaceName>
                </core:output>
            </core:outputs>
            <core:outcomes>
                <core:outcome name="Success"/>
            </core:outcomes>
            <core:sessionManagementType>MAKE_SESSION_IF_NO_CURRENT</core:sessionManagementType>
        </core:metaData>
        <core:outcomeLink>
            <core:linkID>1</core:linkID>
            <core:toStateID>ProductOverview</core:toStateID>
            <core:toActionID></core:toActionID>
            <core:condition></core:condition>
            <core:outcome>Success</core:outcome>
        </core:outcomeLink>
    </core:action>
    <core:action>
        <core:defaultNextStateID></core:defaultNextStateID>
        <core:actionID>GetProductsListFormPreferencesAction</core:actionID>
        <core:name>GetProductsListFormPreferencesAction</core:name>
        <core:className>com.enactor.crm.customerView.actions.GetProductsListFormPreferencesAction</core:className>
        <core:uiHints>
            <entry>
                <key>com.enactor.tools.editor.process.style</key>
                <value>1023</value>
            </entry>
            <entry>
                <key>com.enactor.tools.editor.process.xloc</key>
                <value>937</value>
            </entry>
            <entry>
                <key>com.enactor.tools.editor.process.yloc</key>
                <value>666</value>
            </entry>
        </core:uiHints>
        <core:metaData>
            <core:inputs>
                <core:input required="true" name="enactor.coreUI.List">
                    <core:interfaceName>java.util.List</core:interfaceName>
                </core:input>
            </core:inputs>
            <core:outputs>
                <core:output name="enactor.coreUI.List">
                    <core:interfaceName>java.util.List</core:interfaceName>
                </core:output>
            </core:outputs>
            <core:outcomes>
                <core:outcome name="Success"/>
            </core:outcomes>
            <core:sessionManagementType>MAKE_SESSION_IF_NO_CURRENT</core:sessionManagementType>
        </core:metaData>
        <core:outcomeLink>
            <core:linkID>1</core:linkID>
            <core:toStateID>ProductOverview</core:toStateID>
            <core:toActionID></core:toActionID>
            <core:condition></core:condition>
            <core:outcome>Success</core:outcome>
        </core:outcomeLink>
    </core:action>
    <core:eventLink>
        <core:linkID>1</core:linkID>
        <core:toStateID></core:toStateID>
        <core:toActionID>Cancel</core:toActionID>
        <core:condition></core:condition>
        <core:event>NavigationError</core:event>
    </core:eventLink>
    <core:state>
        <core:url></core:url>
        <core:stateID>Start</core:stateID>
        <core:name></core:name>
        <core:className></core:className>
        <core:defaultNextStateID></core:defaultNextStateID>
        <core:uiHints>
            <entry>
                <key>com.enactor.tools.editor.process.style</key>
                <value>1</value>
            </entry>
            <entry>
                <key>com.enactor.tools.editor.process.xloc</key>
                <value>229</value>
            </entry>
            <entry>
                <key>com.enactor.tools.editor.process.yloc</key>
                <value>68</value>
            </entry>
        </core:uiHints>
        <core:metaData>
            <handledEvents>
                <handledEvent name="StateEntered"/>
            </handledEvents>
            <stateDataTypes/>
        </core:metaData>
        <core:typeId>enactor.types.BasicState</core:typeId>
        <core:singleInstance>false</core:singleInstance>
        <core:respondToViewEvents>false</core:respondToViewEvents>
        <core:actionInputMappings>
            <core:actionMapping>
                <core:actionID>CustomerNumberFilter</core:actionID>
                <core:mappings>
                    <core:processMappings>
                        <core:mappings>
                            <core:sourceDataType required="true" name="enactor.mfc.Customer">
<core:interfaceName>com.enactor.mfc.customer.ICustomer</core:interfaceName>
                            </core:sourceDataType>
                            <core:targetDataType name="enactor.coreUI.DefaultValue">
<core:interfaceName>java.lang.Object</core:interfaceName>
                            </core:targetDataType>
                            <core:expression>customer.customerNumber</core:expression>
                        </core:mappings>
                        <core:mappings>
                            <core:sourceDataType required="true" name="enactor.coreUI.ListCriteria">
<core:interfaceName>com.enactor.core.servers.IListCriteria</core:interfaceName>
                            </core:sourceDataType>
                            <core:targetDataType name="enactor.coreUI.ListCriteria">
<core:interfaceName>com.enactor.core.servers.IListCriteria</core:interfaceName>
                            </core:targetDataType>
                        </core:mappings>
                    </core:processMappings>
                    <core:stateMappings>
                        <core:mappings>
                            <core:targetDataType name="enactor.coreUI.UseKeyForValue">
<core:interfaceName>java.lang.Boolean</core:interfaceName>
                            </core:targetDataType>
                        </core:mappings>
                        <core:mappings>
                            <core:targetDataType name="enactor.coreUI.CaseInsensitive">
<core:interfaceName>java.lang.Boolean</core:interfaceName>
                            </core:targetDataType>
                        </core:mappings>
                        <core:mappings>
                            <core:targetDataType name="enactor.coreUI.MessageId">
<core:interfaceName>java.lang.String</core:interfaceName>
                            </core:targetDataType>
                        </core:mappings>
                        <core:mappings>
                            <core:targetDataType name="enactor.coreUI.MessageBasename">
<core:interfaceName>java.lang.String</core:interfaceName>
                            </core:targetDataType>
                        </core:mappings>
                        <core:mappings>
                            <core:targetDataType name="enactor.coreUI.FilterClassname">
<core:interfaceName>java.lang.String</core:interfaceName>
                            </core:targetDataType>
                        </core:mappings>
                        <core:mappings>
                            <core:targetDataType name="enactor.commonUI.ReadOnly">
<core:interfaceName>java.lang.Boolean</core:interfaceName>
                            </core:targetDataType>
                        </core:mappings>
                        <core:mappings>
                            <core:targetDataType name="enactor.coreUI.ListOrProperties">
<core:interfaceName>java.lang.Boolean</core:interfaceName>
                            </core:targetDataType>
                        </core:mappings>
                        <core:mappings>
                            <core:targetDataType name="enactor.coreUI.ListFilterHidden">
<core:interfaceName>java.lang.Boolean</core:interfaceName>
                            </core:targetDataType>
                        </core:mappings>
                        <core:mappings>
                            <core:targetDataType name="enactor.commonUI.OrNull">
<core:interfaceName>java.lang.Boolean</core:interfaceName>
                            </core:targetDataType>
                        </core:mappings>
                        <core:mappings>
                            <core:targetDataType name="enactor.coreUI.BlankValue">
<core:interfaceName>java.lang.Object</core:interfaceName>
                            </core:targetDataType>
                        </core:mappings>
                        <core:mappings>
                            <core:targetDataType name="enactor.coreUI.ListFilters">
<core:interfaceName>java.util.List</core:interfaceName>
                            </core:targetDataType>
                        </core:mappings>
                        <core:mappings>
                            <core:targetDataType name="enactor.coreUI.FilterKeyProperty">
<core:interfaceName>java.lang.String</core:interfaceName>
                            </core:targetDataType>
                        </core:mappings>
                        <core:mappings>
                            <core:targetDataType name="enactor.coreUI.FuzzyLevel">
<core:interfaceName>java.lang.Integer</core:interfaceName>
                            </core:targetDataType>
                        </core:mappings>
                        <core:mappings>
                            <core:targetDataType name="enactor.commonUI.PersistenceGroupId">
<core:interfaceName>java.lang.String</core:interfaceName>
                            </core:targetDataType>
                        </core:mappings>
                        <core:mappings>
                            <core:targetDataType name="enactor.coreUI.ListFiltersMap">
<core:interfaceName>java.util.Map</core:interfaceName>
                            </core:targetDataType>
                        </core:mappings>
                        <core:mappings>
                            <core:targetDataType name="enactor.coreUI.UseValueForAllProperties">
<core:interfaceName>java.lang.Boolean</core:interfaceName>
                            </core:targetDataType>
                        </core:mappings>
                        <core:mappings>
                            <core:targetDataType name="enactor.coreUI.DefaultToFirstValue">
<core:interfaceName>java.lang.Boolean</core:interfaceName>
                            </core:targetDataType>
                        </core:mappings>
                        <core:mappings>
                            <core:targetDataType name="enactor.commonUI.IgnorePersistenceGroupValues">
<core:interfaceName>java.lang.Boolean</core:interfaceName>
                            </core:targetDataType>
                        </core:mappings>
                        <core:mappings>
                            <core:targetDataType name="enactor.coreUI.ListFilterWidth">
<core:interfaceName>java.lang.Integer</core:interfaceName>
                            </core:targetDataType>
                        </core:mappings>
                        <core:mappings>
                            <core:targetDataType name="enactor.coreUI.CompoundListFilters">
<core:interfaceName>java.util.List</core:interfaceName>
                            </core:targetDataType>
                        </core:mappings>
                        <core:mappings>
                            <core:targetDataType name="enactor.coreUI.ComparisonOperator">
<core:interfaceName>java.lang.Object</core:interfaceName>
                            </core:targetDataType>
                        </core:mappings>
                        <core:mappings>
                            <core:targetDataType name="enactor.commonUI.ForceApplicable">
<core:interfaceName>java.lang.Boolean</core:interfaceName>
                            </core:targetDataType>
                        </core:mappings>
                        <core:mappings>
                            <core:targetDataType name="enactor.coreUI.ValueArray">
<core:interfaceName>java.lang.Object</core:interfaceName>
                            </core:targetDataType>
                        </core:mappings>
                        <core:mappings>
                            <core:targetDataType name="enactor.coreUI.ListAllowBlank">
<core:interfaceName>java.lang.Boolean</core:interfaceName>
                            </core:targetDataType>
                        </core:mappings>
                        <core:mappings>
                            <core:targetDataType name="enactor.coreUI.FilterVariableNames">
<core:interfaceName>java.lang.String</core:interfaceName>
                            </core:targetDataType>
                        </core:mappings>
                        <core:mappings>
                            <core:targetDataType name="enactor.commonUI.ReplaceExistingFilter">
<core:interfaceName>java.lang.Boolean</core:interfaceName>
                            </core:targetDataType>
                        </core:mappings>
                        <core:mappings>
                            <core:targetDataType name="enactor.coreUI.ListName">
<core:interfaceName>java.lang.String</core:interfaceName>
                            </core:targetDataType>
                        </core:mappings>
                        <core:mappings>
                            <core:targetDataType name="enactor.coreUI.EntityNamespace">
<core:interfaceName>java.lang.String</core:interfaceName>
                            </core:targetDataType>
                        </core:mappings>
                        <core:mappings>
                            <core:targetDataType name="enactor.coreUI.EntityName">
<core:interfaceName>java.lang.String</core:interfaceName>
                            </core:targetDataType>
                        </core:mappings>
                    </core:stateMappings>
                </core:mappings>
            </core:actionMapping>
            <core:actionMapping>
                <core:actionID>OptionSetFilter:Suggestions</core:actionID>
                <core:mappings>
                    <core:processMappings>
                        <core:mappings>
                            <core:sourceDataType required="true" name="enactor.coreUI.ListCriteria">
<core:interfaceName>com.enactor.core.servers.IListCriteria</core:interfaceName>
                            </core:sourceDataType>
                            <core:targetDataType name="enactor.coreUI.ListCriteria">
<core:interfaceName>com.enactor.core.servers.IListCriteria</core:interfaceName>
                            </core:targetDataType>
                        </core:mappings>
                    </core:processMappings>
                    <core:stateMappings>
                        <core:mappings>
                            <core:targetDataType name="enactor.coreUI.UseKeyForValue">
<core:interfaceName>java.lang.Boolean</core:interfaceName>
                            </core:targetDataType>
                        </core:mappings>
                        <core:mappings>
                            <core:targetDataType name="enactor.coreUI.CaseInsensitive">
<core:interfaceName>java.lang.Boolean</core:interfaceName>
                            </core:targetDataType>
                        </core:mappings>
                        <core:mappings>
                            <core:targetDataType name="enactor.coreUI.MessageId">
<core:interfaceName>java.lang.String</core:interfaceName>
                            </core:targetDataType>
                        </core:mappings>
                        <core:mappings>
                            <core:targetDataType name="enactor.coreUI.MessageBasename">
<core:interfaceName>java.lang.String</core:interfaceName>
                            </core:targetDataType>
                        </core:mappings>
                        <core:mappings>
                            <core:targetDataType name="enactor.coreUI.FilterClassname">
<core:interfaceName>java.lang.String</core:interfaceName>
                            </core:targetDataType>
                        </core:mappings>
                        <core:mappings>
                            <core:targetDataType name="enactor.commonUI.ReadOnly">
<core:interfaceName>java.lang.Boolean</core:interfaceName>
                            </core:targetDataType>
                        </core:mappings>
                        <core:mappings>
                            <core:targetDataType name="enactor.coreUI.ListOrProperties">
<core:interfaceName>java.lang.Boolean</core:interfaceName>
                            </core:targetDataType>
                        </core:mappings>
                        <core:mappings>
                            <core:targetDataType name="enactor.coreUI.BlankValue">
<core:interfaceName>java.lang.Object</core:interfaceName>
                            </core:targetDataType>
                        </core:mappings>
                        <core:mappings>
                            <core:targetDataType name="enactor.commonUI.OrNull">
<core:interfaceName>java.lang.Boolean</core:interfaceName>
                            </core:targetDataType>
                        </core:mappings>
                        <core:mappings>
                            <core:targetDataType name="enactor.coreUI.ListFilterHidden">
<core:interfaceName>java.lang.Boolean</core:interfaceName>
                            </core:targetDataType>
                        </core:mappings>
                        <core:mappings>
                            <core:targetDataType name="enactor.coreUI.ListFilters">
<core:interfaceName>java.util.List</core:interfaceName>
                            </core:targetDataType>
                        </core:mappings>
                        <core:mappings>
                            <core:targetDataType name="enactor.coreUI.FuzzyLevel">
<core:interfaceName>java.lang.Integer</core:interfaceName>
                            </core:targetDataType>
                        </core:mappings>
                        <core:mappings>
                            <core:targetDataType name="enactor.coreUI.FilterKeyProperty">
<core:interfaceName>java.lang.String</core:interfaceName>
                            </core:targetDataType>
                        </core:mappings>
                        <core:mappings>
                            <core:targetDataType name="enactor.commonUI.PersistenceGroupId">
<core:interfaceName>java.lang.String</core:interfaceName>
                            </core:targetDataType>
                        </core:mappings>
                        <core:mappings>
                            <core:targetDataType name="enactor.coreUI.ListFiltersMap">
<core:interfaceName>java.util.Map</core:interfaceName>
                            </core:targetDataType>
                        </core:mappings>
                        <core:mappings>
                            <core:targetDataType name="enactor.coreUI.UseValueForAllProperties">
<core:interfaceName>java.lang.Boolean</core:interfaceName>
                            </core:targetDataType>
                        </core:mappings>
                        <core:mappings>
                            <core:targetDataType name="enactor.coreUI.DefaultToFirstValue">
<core:interfaceName>java.lang.Boolean</core:interfaceName>
                            </core:targetDataType>
                        </core:mappings>
                        <core:mappings>
                            <core:targetDataType name="enactor.commonUI.IgnorePersistenceGroupValues">
<core:interfaceName>java.lang.Boolean</core:interfaceName>
                            </core:targetDataType>
                        </core:mappings>
                        <core:mappings>
                            <core:targetDataType name="enactor.coreUI.ListFilterWidth">
<core:interfaceName>java.lang.Integer</core:interfaceName>
                            </core:targetDataType>
                        </core:mappings>
                        <core:mappings>
                            <core:targetDataType name="enactor.coreUI.CompoundListFilters">
<core:interfaceName>java.util.List</core:interfaceName>
                            </core:targetDataType>
                        </core:mappings>
                        <core:mappings>
                            <core:targetDataType name="enactor.coreUI.ComparisonOperator">
<core:interfaceName>java.lang.Object</core:interfaceName>
                            </core:targetDataType>
                        </core:mappings>
                        <core:mappings>
                            <core:targetDataType name="enactor.commonUI.ForceApplicable">
<core:interfaceName>java.lang.Boolean</core:interfaceName>
                            </core:targetDataType>
                        </core:mappings>
                        <core:mappings>
                            <core:targetDataType name="enactor.coreUI.ValueArray">
<core:interfaceName>java.lang.Object</core:interfaceName>
                            </core:targetDataType>
                        </core:mappings>
                        <core:mappings>
                            <core:targetDataType name="enactor.coreUI.ListAllowBlank">
<core:interfaceName>java.lang.Boolean</core:interfaceName>
                            </core:targetDataType>
                        </core:mappings>
                        <core:mappings>
                            <core:targetDataType name="enactor.coreUI.FilterVariableNames">
<core:interfaceName>java.lang.String</core:interfaceName>
                            </core:targetDataType>
                        </core:mappings>
                        <core:mappings>
                            <core:targetDataType name="enactor.commonUI.ReplaceExistingFilter">
<core:interfaceName>java.lang.Boolean</core:interfaceName>
                            </core:targetDataType>
                        </core:mappings>
                        <core:mappings>
                            <core:targetDataType name="enactor.coreUI.EntityNamespace">
<core:interfaceName>java.lang.String</core:interfaceName>
                            </core:targetDataType>
                        </core:mappings>
                        <core:mappings>
                            <core:targetDataType name="enactor.coreUI.ListName">
<core:interfaceName>java.lang.String</core:interfaceName>
                            </core:targetDataType>
                        </core:mappings>
                        <core:mappings>
                            <core:targetDataType name="enactor.coreUI.EntityName">
<core:interfaceName>java.lang.String</core:interfaceName>
                            </core:targetDataType>
                        </core:mappings>
                    </core:stateMappings>
                </core:mappings>
            </core:actionMapping>
            <core:actionMapping>
                <core:actionID>GetProductsListFormPreferencesAction</core:actionID>
                <core:mappings>
                    <core:processMappings>
                        <core:mappings>
                            <core:sourceDataType required="true" name="enactor.mfc.CustomerPreferenceList">
<core:interfaceName>java.util.List</core:interfaceName>
                            </core:sourceDataType>
                            <core:targetDataType required="true" name="enactor.coreUI.List">
<core:interfaceName>java.util.List</core:interfaceName>
                            </core:targetDataType>
                        </core:mappings>
                    </core:processMappings>
                    <core:stateMappings/>
                </core:mappings>
            </core:actionMapping>
        </core:actionInputMappings>
        <core:actionOutputMappings>
            <core:actionMapping>
                <core:actionID>CustomerNumberFilter</core:actionID>
                <core:mappings>
                    <core:processMappings>
                        <core:mappings>
                            <core:sourceDataType name="enactor.coreUI.ListCriteria">
<core:interfaceName>com.enactor.core.servers.IListCriteria</core:interfaceName>
                            </core:sourceDataType>
                            <core:targetDataType required="true" name="enactor.coreUI.ListCriteria">
<core:interfaceName>com.enactor.core.servers.IListCriteria</core:interfaceName>
                            </core:targetDataType>
                        </core:mappings>
                    </core:processMappings>
                    <core:stateMappings>
                        <core:mappings>
                            <core:sourceDataType name="enactor.coreUI.ListFilter">
<core:interfaceName>com.enactor.core.listFilters.IListFilter</core:interfaceName>
                            </core:sourceDataType>
                        </core:mappings>
                        <core:mappings>
                            <core:sourceDataType name="enactor.coreUI.ListFilters">
<core:interfaceName>java.util.List</core:interfaceName>
                            </core:sourceDataType>
                        </core:mappings>
                        <core:mappings>
                            <core:sourceDataType name="enactor.coreUI.ListFiltersMap">
<core:interfaceName>java.util.Map</core:interfaceName>
                            </core:sourceDataType>
                        </core:mappings>
                    </core:stateMappings>
                </core:mappings>
            </core:actionMapping>
            <core:actionMapping>
                <core:actionID>OptionSetFilter:Suggestions</core:actionID>
                <core:mappings>
                    <core:processMappings>
                        <core:mappings>
                            <core:sourceDataType name="enactor.coreUI.ListCriteria">
<core:interfaceName>com.enactor.core.servers.IListCriteria</core:interfaceName>
                            </core:sourceDataType>
                            <core:targetDataType required="true" name="enactor.coreUI.ListCriteria">
<core:interfaceName>com.enactor.core.servers.IListCriteria</core:interfaceName>
                            </core:targetDataType>
                        </core:mappings>
                    </core:processMappings>
                    <core:stateMappings>
                        <core:mappings>
                            <core:sourceDataType name="enactor.coreUI.ListFilter">
<core:interfaceName>com.enactor.core.listFilters.IListFilter</core:interfaceName>
                            </core:sourceDataType>
                        </core:mappings>
                        <core:mappings>
                            <core:sourceDataType name="enactor.coreUI.ListFilters">
<core:interfaceName>java.util.List</core:interfaceName>
                            </core:sourceDataType>
                        </core:mappings>
                        <core:mappings>
                            <core:sourceDataType name="enactor.coreUI.ListFiltersMap">
<core:interfaceName>java.util.Map</core:interfaceName>
                            </core:sourceDataType>
                        </core:mappings>
                    </core:stateMappings>
                </core:mappings>
            </core:actionMapping>
            <core:actionMapping>
                <core:actionID>InvokeLoadCustomerPreference</core:actionID>
                <core:mappings>
                    <core:processMappings>
                        <core:mappings>
                            <core:sourceDataType required="true" name="enactor.coreUI.ListCriteria">
<core:interfaceName>com.enactor.core.servers.IListCriteria</core:interfaceName>
                            </core:sourceDataType>
                            <core:targetDataType required="true" name="enactor.coreUI.ListCriteria">
<core:interfaceName>com.enactor.core.servers.IListCriteria</core:interfaceName>
                            </core:targetDataType>
                        </core:mappings>
                        <core:mappings>
                            <core:sourceDataType required="true" name="enactor.coreUI.List">
<core:interfaceName>java.util.List</core:interfaceName>
                            </core:sourceDataType>
                            <core:targetDataType required="true" name="enactor.mfc.CustomerPreferenceList">
<core:interfaceName>java.util.List</core:interfaceName>
                            </core:targetDataType>
                        </core:mappings>
                    </core:processMappings>
                    <core:stateMappings/>
                </core:mappings>
            </core:actionMapping>
            <core:actionMapping>
                <core:actionID>CallLoadCustomerPreferences</core:actionID>
                <core:mappings>
                    <core:processMappings>
                        <core:mappings>
                            <core:sourceDataType required="false" name="enactor.coreUI.List">
<core:interfaceName>java.util.List</core:interfaceName>
                            </core:sourceDataType>
                            <core:targetDataType required="true" name="enactor.mfc.CustomerPreferenceList">
<core:interfaceName>java.util.List</core:interfaceName>
                            </core:targetDataType>
                        </core:mappings>
                    </core:processMappings>
                    <core:stateMappings/>
                </core:mappings>
            </core:actionMapping>
        </core:actionOutputMappings>
        <core:eventLink>
            <core:linkID>1</core:linkID>
            <core:toStateID></core:toStateID>
            <core:toActionID>CustomerNumberFilter</core:toActionID>
            <core:condition></core:condition>
            <core:event>StateEntered</core:event>
        </core:eventLink>
    </core:state>
    <core:promptState>
        <core:url>CRM/Customer/ProductsOverview</core:url>
        <core:stateID>ProductOverview</core:stateID>
        <core:name></core:name>
        <core:className>com.enactor.coreUI.states.UIPromptState</core:className>
        <core:defaultNextStateID></core:defaultNextStateID>
        <core:uiHints>
            <entry>
                <key>com.enactor.tools.editor.process.style</key>
                <value>1023</value>
            </entry>
            <entry>
                <key>com.enactor.tools.editor.process.xloc</key>
                <value>937</value>
            </entry>
            <entry>
                <key>com.enactor.tools.editor.process.yloc</key>
                <value>191</value>
            </entry>
        </core:uiHints>
        <core:metaData>
            <core:inputs>
                <core:input required="true" name="enactor.crm.customerLoyalty.CustomerLoyaltyDetailType">
                    <core:interfaceName>com.enactor.crm.customerLoyalty.ICustomerLoyaltyDetailResponse</core:interfaceName>
                </core:input>
                <core:input required="true" name="enactor.mfc.Customer">
                    <core:interfaceName>com.enactor.mfc.customer.ICustomer</core:interfaceName>
                </core:input>
                <core:input required="true" name="enactor.mfc.BaseCurrency">
                    <core:interfaceName>com.enactor.mfc.currency.ICurrency</core:interfaceName>
                </core:input>
                <core:input required="true" name="enactor.coreUI.URL">
                    <core:interfaceName>java.lang.String</core:interfaceName>
                </core:input>
                <core:input required="true" name="enactor.coreUI.List">
                    <core:interfaceName>java.util.List</core:interfaceName>
                </core:input>
            </core:inputs>
            <core:outputs>
                <core:output required="true" name="enactor.mfc.ProductId">
                    <core:interfaceName>java.lang.String</core:interfaceName>
                </core:output>
            </core:outputs>
            <handledEvents>
                <handledEvent name="CancelPressed"/>
                <handledEvent name="ViewWishList"/>
                <handledEvent name="RefreshProductList"/>
                <handledEvent name="ViewProduct"/>
            </handledEvents>
            <stateDataTypes>
                <stateDataType required="true" name="enactor.mfc.ProductId">
                    <core:interfaceName>java.lang.String</core:interfaceName>
                </stateDataType>
                <stateDataType required="true" name="enactor.crm.customerLoyalty.CustomerLoyaltyDetailType">
                    <core:interfaceName>com.enactor.crm.customerLoyalty.ICustomerLoyaltyDetailResponse</core:interfaceName>
                </stateDataType>
                <stateDataType required="true" name="enactor.mfc.Customer">
                    <core:interfaceName>com.enactor.mfc.customer.ICustomer</core:interfaceName>
                </stateDataType>
                <stateDataType required="true" name="enactor.mfc.BaseCurrency">
                    <core:interfaceName>com.enactor.mfc.currency.ICurrency</core:interfaceName>
                </stateDataType>
                <stateDataType required="true" name="enactor.coreUI.URL">
                    <core:interfaceName>java.lang.String</core:interfaceName>
                </stateDataType>
                <stateDataType required="true" name="enactor.coreUI.List">
                    <core:interfaceName>java.util.List</core:interfaceName>
                </stateDataType>
            </stateDataTypes>
        </core:metaData>
        <core:typeId>enactor.types.PromptState</core:typeId>
        <core:singleInstance>false</core:singleInstance>
        <core:respondToViewEvents>false</core:respondToViewEvents>
        <core:stateInputMappings>
            <core:mappings>
                <core:sourceDataType required="true" name="enactor.mfc.Customer">
                    <core:interfaceName>com.enactor.mfc.customer.ICustomer</core:interfaceName>
                </core:sourceDataType>
                <core:targetDataType required="true" name="enactor.mfc.Customer">
                    <core:interfaceName>com.enactor.mfc.customer.ICustomer</core:interfaceName>
                </core:targetDataType>
            </core:mappings>
            <core:mappings>
                <core:sourceDataType required="true" name="enactor.mfc.BaseCurrency">
                    <core:interfaceName>com.enactor.mfc.currency.ICurrency</core:interfaceName>
                </core:sourceDataType>
                <core:targetDataType required="true" name="enactor.mfc.BaseCurrency">
                    <core:interfaceName>com.enactor.mfc.currency.ICurrency</core:interfaceName>
                </core:targetDataType>
            </core:mappings>
            <core:mappings>
                <core:sourceDataType required="true" name="enactor.coreUI.URL">
                    <core:interfaceName>java.lang.String</core:interfaceName>
                </core:sourceDataType>
                <core:targetDataType required="true" name="enactor.coreUI.URL">
                    <core:interfaceName>java.lang.String</core:interfaceName>
                </core:targetDataType>
            </core:mappings>
            <core:mappings>
                <core:sourceDataType required="true" name="enactor.coreUI.List">
                    <core:interfaceName>java.util.List</core:interfaceName>
                </core:sourceDataType>
                <core:targetDataType required="true" name="enactor.coreUI.List">
                    <core:interfaceName>java.util.List</core:interfaceName>
                </core:targetDataType>
            </core:mappings>
            <core:mappings>
                <core:sourceDataType required="true" name="enactor.customerMaintenance.CustomerLoyaltyDetailResponse">
                    <core:interfaceName>com.enactor.crm.customerLoyalty.ICustomerLoyaltyDetailResponse</core:interfaceName>
                </core:sourceDataType>
                <core:targetDataType required="true" name="enactor.crm.customerLoyalty.CustomerLoyaltyDetailType">
                    <core:interfaceName>com.enactor.crm.customerLoyalty.ICustomerLoyaltyDetailResponse</core:interfaceName>
                </core:targetDataType>
            </core:mappings>
        </core:stateInputMappings>
        <core:actionInputMappings>
            <core:actionMapping>
                <core:actionID>ReLoadProductsListFormPreferencesAction</core:actionID>
                <core:mappings>
                    <core:processMappings>
                        <core:mappings>
                            <core:sourceDataType required="true" name="enactor.mfc.CustomerPreferenceList">
<core:interfaceName>java.util.List</core:interfaceName>
                            </core:sourceDataType>
                            <core:targetDataType required="true" name="enactor.coreUI.List">
<core:interfaceName>java.util.List</core:interfaceName>
                            </core:targetDataType>
                        </core:mappings>
                    </core:processMappings>
                    <core:stateMappings/>
                </core:mappings>
            </core:actionMapping>
        </core:actionInputMappings>
        <core:actionOutputMappings>
            <core:actionMapping>
                <core:actionID>ReLoadCustomerPreferences</core:actionID>
                <core:mappings>
                    <core:processMappings>
                        <core:mappings>
                            <core:sourceDataType required="false" name="enactor.coreUI.List">
<core:interfaceName>java.util.List</core:interfaceName>
                            </core:sourceDataType>
                            <core:targetDataType required="true" name="enactor.mfc.CustomerPreferenceList">
<core:interfaceName>java.util.List</core:interfaceName>
                            </core:targetDataType>
                        </core:mappings>
                    </core:processMappings>
                    <core:stateMappings/>
                </core:mappings>
            </core:actionMapping>
        </core:actionOutputMappings>
        <core:eventLink>
            <core:linkID>1</core:linkID>
            <core:toStateID></core:toStateID>
            <core:toActionID>Cancel</core:toActionID>
            <core:condition></core:condition>
            <core:event>CancelPressed</core:event>
        </core:eventLink>
        <core:eventLink>
            <core:linkID>2</core:linkID>
            <core:toStateID>ProductDetails</core:toStateID>
            <core:toActionID></core:toActionID>
            <core:condition></core:condition>
            <core:event>ViewProduct</core:event>
        </core:eventLink>
        <core:eventLink>
            <core:linkID>4</core:linkID>
            <core:toStateID></core:toStateID>
            <core:toActionID>View Wish List</core:toActionID>
            <core:condition></core:condition>
            <core:event>ViewWishList</core:event>
        </core:eventLink>
        <core:eventLink>
            <core:linkID>3</core:linkID>
            <core:toStateID></core:toStateID>
            <core:toActionID>ReLoadCustomerPreferences</core:toActionID>
            <core:condition></core:condition>
            <core:event>RefreshProductList</core:event>
        </core:eventLink>
        <core:keepPromptOpen>false</core:keepPromptOpen>
        <core:keepPreviousPromptOpen>false</core:keepPreviousPromptOpen>
        <core:promptTimeout>0</core:promptTimeout>
        <core:hideOpenPrompt>false</core:hideOpenPrompt>
        <core:allowDatabasePromptLookup>false</core:allowDatabasePromptLookup>
    </core:promptState>
    <core:promptState>
        <core:url>CRM/Customer/ProductDetails</core:url>
        <core:stateID>ProductDetails</core:stateID>
        <core:name></core:name>
        <core:className>com.enactor.coreUI.states.UIPromptState</core:className>
        <core:defaultNextStateID></core:defaultNextStateID>
        <core:uiHints>
            <entry>
                <key>com.enactor.tools.editor.process.style</key>
                <value>1023</value>
            </entry>
            <entry>
                <key>com.enactor.tools.editor.process.xloc</key>
                <value>1424</value>
            </entry>
            <entry>
                <key>com.enactor.tools.editor.process.yloc</key>
                <value>471</value>
            </entry>
        </core:uiHints>
        <core:metaData>
            <core:inputs>
                <core:input required="true" name="enactor.mfc.ProductId">
                    <core:interfaceName>java.lang.String</core:interfaceName>
                </core:input>
                <core:input required="true" name="enactor.crm.customerLoyalty.CustomerLoyaltyDetailType">
                    <core:interfaceName>com.enactor.crm.customerLoyalty.ICustomerLoyaltyDetailResponse</core:interfaceName>
                </core:input>
                <core:input required="true" name="enactor.mfc.Customer">
                    <core:interfaceName>com.enactor.mfc.customer.ICustomer</core:interfaceName>
                </core:input>
                <core:input required="true" name="enactor.mfc.BaseCurrency">
                    <core:interfaceName>com.enactor.mfc.currency.ICurrency</core:interfaceName>
                </core:input>
                <core:input required="true" name="enactor.coreUI.URL">
                    <core:interfaceName>java.lang.String</core:interfaceName>
                </core:input>
            </core:inputs>
            <handledEvents>
                <handledEvent name="CancelPressed"/>
                <handledEvent name="AddToWishList"/>
                <handledEvent name="RemoveProduct"/>
                <handledEvent name="StateEntered"/>
            </handledEvents>
            <stateDataTypes>
                <stateDataType required="true" name="enactor.crm.CurrentPic">
                    <core:interfaceName>java.lang.Object</core:interfaceName>
                </stateDataType>
                <stateDataType required="true" name="enactor.crmClientelingServices.ProductEnquiryResponse">
                    <core:interfaceName>com.enactor.mfc.product.enquiry.IProductEnquiryResponse</core:interfaceName>
                </stateDataType>
                <stateDataType required="true" name="enactor.crm.ImagesList">
                    <core:interfaceName>java.util.List</core:interfaceName>
                </stateDataType>
                <stateDataType required="true" name="enactor.mfc.ProductKey">
                    <core:interfaceName>com.enactor.mfc.product.IProductKey</core:interfaceName>
                </stateDataType>
                <stateDataType required="true" name="enactor.mfc.ProductId">
                    <core:interfaceName>java.lang.String</core:interfaceName>
                </stateDataType>
                <stateDataType required="true" name="enactor.mfc.Product">
                    <core:interfaceName>com.enactor.mfc.product.IProduct</core:interfaceName>
                </stateDataType>
                <stateDataType required="true" name="enactor.crm.customerLoyalty.CustomerLoyaltyDetailType">
                    <core:interfaceName>com.enactor.crm.customerLoyalty.ICustomerLoyaltyDetailResponse</core:interfaceName>
                </stateDataType>
                <stateDataType required="true" name="enactor.mfc.Customer">
                    <core:interfaceName>com.enactor.mfc.customer.ICustomer</core:interfaceName>
                </stateDataType>
                <stateDataType required="true" name="enactor.mfc.BaseCurrency">
                    <core:interfaceName>com.enactor.mfc.currency.ICurrency</core:interfaceName>
                </stateDataType>
                <stateDataType required="true" name="enactor.coreUI.URL">
                    <core:interfaceName>java.lang.String</core:interfaceName>
                </stateDataType>
            </stateDataTypes>
        </core:metaData>
        <core:typeId>enactor.types.PromptState</core:typeId>
        <core:singleInstance>false</core:singleInstance>
        <core:respondToViewEvents>false</core:respondToViewEvents>
        <core:stateInputMappings>
            <core:mappings>
                <core:sourceDataType required="true" name="enactor.mfc.Customer">
                    <core:interfaceName>com.enactor.mfc.customer.ICustomer</core:interfaceName>
                </core:sourceDataType>
                <core:targetDataType required="true" name="enactor.mfc.Customer">
                    <core:interfaceName>com.enactor.mfc.customer.ICustomer</core:interfaceName>
                </core:targetDataType>
            </core:mappings>
            <core:mappings>
                <core:sourceDataType required="true" name="enactor.mfc.BaseCurrency">
                    <core:interfaceName>com.enactor.mfc.currency.ICurrency</core:interfaceName>
                </core:sourceDataType>
                <core:targetDataType required="true" name="enactor.mfc.BaseCurrency">
                    <core:interfaceName>com.enactor.mfc.currency.ICurrency</core:interfaceName>
                </core:targetDataType>
            </core:mappings>
            <core:mappings>
                <core:sourceDataType required="true" name="enactor.coreUI.URL">
                    <core:interfaceName>java.lang.String</core:interfaceName>
                </core:sourceDataType>
                <core:targetDataType required="true" name="enactor.coreUI.URL">
                    <core:interfaceName>java.lang.String</core:interfaceName>
                </core:targetDataType>
            </core:mappings>
            <core:mappings>
                <core:sourceDataType required="true" name="enactor.customerMaintenance.CustomerLoyaltyDetailResponse">
                    <core:interfaceName>com.enactor.crm.customerLoyalty.ICustomerLoyaltyDetailResponse</core:interfaceName>
                </core:sourceDataType>
                <core:targetDataType required="true" name="enactor.crm.customerLoyalty.CustomerLoyaltyDetailType">
                    <core:interfaceName>com.enactor.crm.customerLoyalty.ICustomerLoyaltyDetailResponse</core:interfaceName>
                </core:targetDataType>
            </core:mappings>
            <core:mappings>
                <core:targetDataType required="true" name="enactor.mfc.ProductId">
                    <core:interfaceName>java.lang.String</core:interfaceName>
                </core:targetDataType>
            </core:mappings>
        </core:stateInputMappings>
        <core:actionInputMappings>
            <core:actionMapping>
                <core:actionID>InvokeProductEnquiry</core:actionID>
                <core:mappings>
                    <core:processMappings>
                        <core:mappings>
                            <core:sourceDataType required="true" name="enactor.mfc.Device">
<core:interfaceName>com.enactor.mfc.device.IDevice</core:interfaceName>
                            </core:sourceDataType>
                            <core:targetDataType required="true" name="enactor.mfc.Device">
<core:interfaceName>com.enactor.mfc.device.IDevice</core:interfaceName>
                            </core:targetDataType>
                        </core:mappings>
                        <core:mappings>
                            <core:sourceDataType required="true" name="enactor.mfc.Location">
<core:interfaceName>com.enactor.mfc.location.ILocation</core:interfaceName>
                            </core:sourceDataType>
                            <core:targetDataType required="true" name="enactor.mfc.Location">
<core:interfaceName>com.enactor.mfc.location.ILocation</core:interfaceName>
                            </core:targetDataType>
                        </core:mappings>
                    </core:processMappings>
                    <core:stateMappings>
                        <core:mappings>
                            <core:targetDataType name="enactor.productSearch.UserId">
<core:interfaceName>java.lang.String</core:interfaceName>
                            </core:targetDataType>
                        </core:mappings>
                        <core:mappings>
                            <core:sourceDataType required="true" name="enactor.mfc.ProductId">
<core:interfaceName>java.lang.String</core:interfaceName>
                            </core:sourceDataType>
                            <core:targetDataType required="true" name="enactor.productSearch.ProductId">
<core:interfaceName>java.lang.String</core:interfaceName>
                            </core:targetDataType>
                        </core:mappings>
                    </core:stateMappings>
                </core:mappings>
            </core:actionMapping>
            <core:actionMapping>
                <core:actionID>RemoveProductFromCustomerPreference</core:actionID>
                <core:mappings>
                    <core:processMappings>
                        <core:mappings>
                            <core:sourceDataType required="true" name="enactor.mfc.CustomerPreferenceList">
<core:interfaceName>java.util.List</core:interfaceName>
                            </core:sourceDataType>
                            <core:targetDataType required="true" name="enactor.coreUI.List">
<core:interfaceName>java.util.List</core:interfaceName>
                            </core:targetDataType>
                        </core:mappings>
                    </core:processMappings>
                    <core:stateMappings>
                        <core:mappings>
                            <core:sourceDataType required="true" name="enactor.mfc.ProductId">
<core:interfaceName>java.lang.String</core:interfaceName>
                            </core:sourceDataType>
                            <core:targetDataType required="true" name="enactor.mfc.ProductId">
<core:interfaceName>java.lang.String</core:interfaceName>
                            </core:targetDataType>
                        </core:mappings>
                    </core:stateMappings>
                </core:mappings>
            </core:actionMapping>
            <core:actionMapping>
                <core:actionID>AddProductToCustomerWishList</core:actionID>
                <core:mappings>
                    <core:processMappings>
                        <core:mappings>
                            <core:sourceDataType required="true" name="enactor.mfc.Device">
<core:interfaceName>com.enactor.mfc.device.IDevice</core:interfaceName>
                            </core:sourceDataType>
                            <core:targetDataType required="true" name="enactor.mfc.Device">
<core:interfaceName>com.enactor.mfc.device.IDevice</core:interfaceName>
                            </core:targetDataType>
                        </core:mappings>
                        <core:mappings>
                            <core:sourceDataType required="true" name="enactor.mfc.Customer">
<core:interfaceName>com.enactor.mfc.customer.ICustomer</core:interfaceName>
                            </core:sourceDataType>
                            <core:targetDataType required="true" name="enactor.mfc.CustomerKey">
<core:interfaceName>com.enactor.mfc.customer.ICustomerKey</core:interfaceName>
                            </core:targetDataType>
                            <core:expression>customer.key</core:expression>
                        </core:mappings>
                    </core:processMappings>
                    <core:stateMappings>
                        <core:mappings>
                            <core:sourceDataType required="true" name="enactor.crmClientelingServices.ProductEnquiryResponse">
<core:interfaceName>com.enactor.mfc.product.enquiry.IProductEnquiryResponse</core:interfaceName>
                            </core:sourceDataType>
                            <core:targetDataType required="true" name="enactor.mfc.ProductDescription">
<core:interfaceName>java.lang.String</core:interfaceName>
                            </core:targetDataType>
                            <core:expression>productEnquiryResponse.description</core:expression>
                        </core:mappings>
                        <core:mappings>
                            <core:sourceDataType required="true" name="enactor.mfc.ProductId">
<core:interfaceName>java.lang.String</core:interfaceName>
                            </core:sourceDataType>
                            <core:targetDataType required="true" name="enactor.mfc.ProductId">
<core:interfaceName>java.lang.String</core:interfaceName>
                            </core:targetDataType>
                        </core:mappings>
                    </core:stateMappings>
                </core:mappings>
            </core:actionMapping>
            <core:actionMapping>
                <core:actionID>ReLoadProductsListFormPreferencesAction</core:actionID>
                <core:mappings>
                    <core:processMappings>
                        <core:mappings>
                            <core:sourceDataType required="true" name="enactor.mfc.CustomerPreferenceList">
<core:interfaceName>java.util.List</core:interfaceName>
                            </core:sourceDataType>
                            <core:targetDataType required="true" name="enactor.coreUI.List">
<core:interfaceName>java.util.List</core:interfaceName>
                            </core:targetDataType>
                        </core:mappings>
                    </core:processMappings>
                    <core:stateMappings/>
                </core:mappings>
            </core:actionMapping>
        </core:actionInputMappings>
        <core:actionOutputMappings>
            <core:actionMapping>
                <core:actionID>InvokeProductEnquiry</core:actionID>
                <core:mappings>
                    <core:processMappings/>
                    <core:stateMappings>
                        <core:mappings>
                            <core:sourceDataType required="true" name="enactor.productSearch.ProductEnquiryResponse">
<core:interfaceName>com.enactor.mfc.product.enquiry.IProductEnquiryResponse</core:interfaceName>
                            </core:sourceDataType>
                            <core:targetDataType required="true" name="enactor.crmClientelingServices.ProductEnquiryResponse">
<core:interfaceName>com.enactor.mfc.product.enquiry.IProductEnquiryResponse</core:interfaceName>
                            </core:targetDataType>
                        </core:mappings>
                        <core:mappings>
                            <core:sourceDataType required="true" name="enactor.productSearch.ProductEnquiryResponse">
<core:interfaceName>com.enactor.mfc.product.enquiry.IProductEnquiryResponse</core:interfaceName>
                            </core:sourceDataType>
                            <core:targetDataType required="true" name="enactor.mfc.ProductKey">
<core:interfaceName>com.enactor.mfc.product.IProductKey</core:interfaceName>
                            </core:targetDataType>
                        </core:mappings>
                    </core:stateMappings>
                </core:mappings>
            </core:actionMapping>
        </core:actionOutputMappings>
        <core:eventLink>
            <core:linkID>1</core:linkID>
            <core:toStateID>ProductOverview</core:toStateID>
            <core:toActionID></core:toActionID>
            <core:condition></core:condition>
            <core:event>CancelPressed</core:event>
        </core:eventLink>
        <core:eventLink>
            <core:linkID>2</core:linkID>
            <core:toStateID></core:toStateID>
            <core:toActionID>RemoveProductFromCustomerPreference</core:toActionID>
            <core:condition></core:condition>
            <core:event>RemoveProduct</core:event>
        </core:eventLink>
        <core:eventLink>
            <core:linkID>5</core:linkID>
            <core:toStateID></core:toStateID>
            <core:toActionID>InvokeProductEnquiry</core:toActionID>
            <core:condition></core:condition>
            <core:event>StateEntered</core:event>
        </core:eventLink>
        <core:eventLink>
            <core:linkID>3</core:linkID>
            <core:toStateID></core:toStateID>
            <core:toActionID>AddProductToCustomerWishList</core:toActionID>
            <core:condition></core:condition>
            <core:event>AddToWishList</core:event>
        </core:eventLink>
        <core:keepPromptOpen>false</core:keepPromptOpen>
        <core:keepPreviousPromptOpen>false</core:keepPreviousPromptOpen>
        <core:promptTimeout>0</core:promptTimeout>
        <core:hideOpenPrompt>false</core:hideOpenPrompt>
        <core:allowDatabasePromptLookup>false</core:allowDatabasePromptLookup>
    </core:promptState>
    <core:stateTransitions/>
</core:process>
